nanowire_flask/__init__.py
nanowire_flask/csv_tools/__init__.py
nanowire_flask/file_tools/__init__.py
nanowire_flask/image_tools/__init__.py
nanowire_flask/json_tools/__init__.py
nanowire_flask/text_tools/__init__.py
nanowire_flask-0.1.0.data/data/README.md
nanowire_flask-0.1.0.data/data/VERSION
nanowire_flask-0.1.0.dist-info/DESCRIPTION.rst
nanowire_flask-0.1.0.dist-info/METADATA
nanowire_flask-0.1.0.dist-info/RECORD
nanowire_flask-0.1.0.dist-info/WHEEL
nanowire_flask-0.1.0.dist-info/metadata.json
nanowire_flask-0.1.0.dist-info/top_level.txt
