Metadata-Version: 2.0
Name: nanowire-flask
Version: 0.1.0
Summary: Tool for creating nanowire tools with the flask structure.
Home-page: https://github.com/SpotlightData/nanowire_flask
Author: Stuart Bowe
Author-email: stuart@spotlightdata.co.uk
License: MIT
Keywords: flask,API,nanowire,spotlight data
Platform: UNKNOWN
Requires-Python: >=3.5
Requires-Dist: Pillow (>=5.4.1)
Requires-Dist: requests (>=2.21.0)
Requires-Dist: Flask-API (>=1.1)
Requires-Dist: jsonpickle (>=1.1)
Requires-Dist: psutil (>=5.5.0)
Requires-Dist: pandas (>=0.23.4)
Requires-Dist: xlrd (>=1.0.0)
